Hellf
